oddorevenfebin/__init__.py
oddorevenfebin/checker.py
oddorevenfebin-0.1.0.dist-info/METADATA
oddorevenfebin-0.1.0.dist-info/WHEEL
oddorevenfebin-0.1.0.dist-info/top_level.txt
oddorevenfebin-0.1.0.dist-info/RECORD
