Metadata-Version: 2.4
Name: oddorevenfebin
Version: 0.1.0
Summary: A package to check whether a number is odd or even
Author-email: Febin Sunny <febinsunny2004@gmail.com>
Keywords: odd,even,math,checker
Classifier: Programming Language :: Python :: 3
Classifier: License :: OSI Approved :: MIT License
Classifier: Operating System :: OS Independent
Requires-Python: >=3.7
